pymbda/__init__.py
pymbda/__main__.py
pymbda/commands.py
pymbda/dtypes.py
pymbda/templates.py
pymbda/utils.py
pymbda-0.3.1.dist-info/LICENSE
pymbda-0.3.1.dist-info/METADATA
pymbda-0.3.1.dist-info/WHEEL
pymbda-0.3.1.dist-info/entry_points.txt
pymbda-0.3.1.dist-info/top_level.txt
pymbda-0.3.1.dist-info/zip-safe
pymbda-0.3.1.dist-info/RECORD
